hydration/__init__.py
hydration/base.py
hydration/endianness.py
hydration/fields.py
hydration/helpers.py
hydration/message.py
hydration/scalars.py
hydration/validators.py
hydration/vectors.py
hydration-4.0.0.dist-info/LICENSE
hydration-4.0.0.dist-info/METADATA
hydration-4.0.0.dist-info/WHEEL
hydration-4.0.0.dist-info/top_level.txt
hydration-4.0.0.dist-info/RECORD
