Metadata-Version: 2.1
Name: hydration
Version: 4.0.0
Summary: A module used to define python objects that can be converted to (and from) bytes.
Home-page: https://github.com/shustinm/hydration
Author: Michael Shustin
Author-email: michaelshustin@gmail.com
License: UNKNOWN
Platform: UNKNOWN
Classifier: Programming Language :: Python :: 3
Classifier: Development Status :: 5 - Production/Stable
Classifier: License :: OSI Approved :: GNU Affero General Public License v3
Classifier: Operating System :: OS Independent
Requires-Python: >=3.6
Requires-Dist: pyhooks (>=1.0.3)
